blendedUx/__init__.py
blendedUx/blended_flask/__init__.py
blendedUx/blended_flask/app.py
blendedUx/blended_flask/functions.py
blendedUx/blended_flask/settings.py
blendedUx/blended_flask/utils.py
blendedUx/blended_hostlib/__init__.py
blendedUx/blended_hostlib/initializer.py
blendedUx/blended_hostlib/tests.py
blendedUx/blended_hostlib/transform_image.py
blendedUx/blended_hostlib/backend/__init__.py
blendedUx/blended_hostlib/backend/backend.py
blendedUx/blended_hostlib/backend/intermediary.py
blendedUx/blended_hostlib/backend/settings.py
blendedUx/blended_hostlib/controller/__init__.py
blendedUx/blended_hostlib/controller/controller.py
blendedUx/blended_hostlib/exceptions/__init__.py
blendedUx/blended_hostlib/exceptions/exceptions.py
blendedUx/blended_hostlib/functions/__init__.py
blendedUx/blended_hostlib/functions/functions.py
blendedUx/blended_hostlib/network/__init__.py
blendedUx/blended_hostlib/network/network.py
blendedUx/blended_hostlib/network/settings.py
blendedUx/blended_hostlib/swagger_client/__init__.py
blendedUx/blended_hostlib/swagger_client/api_client.py
blendedUx/blended_hostlib/swagger_client/configuration.py
blendedUx/blended_hostlib/swagger_client/rest.py
blendedUx/blended_hostlib/swagger_client/apis/__init__.py
blendedUx/blended_hostlib/swagger_client/apis/accounts_api.py
blendedUx/blended_hostlib/swagger_client/apis/packages_api.py
blendedUx/blended_hostlib/swagger_client/models/__init__.py
blendedUx/blended_hostlib/swagger_client/models/account.py
blendedUx/blended_hostlib/swagger_client/models/account_invite_pending.py
blendedUx/blended_hostlib/swagger_client/models/account_invites_pending_list.py
blendedUx/blended_hostlib/swagger_client/models/accounts.py
blendedUx/blended_hostlib/swagger_client/models/acquisition.py
blendedUx/blended_hostlib/swagger_client/models/acquisition_response.py
blendedUx/blended_hostlib/swagger_client/models/acquisition_response_data.py
blendedUx/blended_hostlib/swagger_client/models/activationchallenge.py
mahendra_blendedUx-0.0.3.dist-info/METADATA
mahendra_blendedUx-0.0.3.dist-info/WHEEL
mahendra_blendedUx-0.0.3.dist-info/entry_points.txt
mahendra_blendedUx-0.0.3.dist-info/top_level.txt
mahendra_blendedUx-0.0.3.dist-info/RECORD
